<?xml version="1.0" encoding="UTF-8"?>
<objects serializationModel="Studio.02.02.00">
	<object class="AudioFile" id="{647884cb-4965-4d40-b967-f68901573c4f}">
		<property name="assetPath">
			<value>Ootsa_Annoyed2.mp3</value>
		</property>
		<property name="frequencyInKHz">
			<value>44.0999985</value>
		</property>
		<property name="channelCount">
			<value>2</value>
		</property>
		<property name="length">
			<value>1.5673469387755101</value>
		</property>
		<relationship name="masterAssetFolder">
			<destination>{d72e42ed-61d3-471d-9c5a-b5cebd374c05}</destination>
		</relationship>
	</object>
</objects>
