<?xml version="1.0" encoding="UTF-8"?>
<objects serializationModel="Studio.02.02.00">
	<object class="AudioFile" id="{d6490162-668c-43ed-8b5e-cdda231116e6}">
		<property name="assetPath">
			<value>Bard Sad Line 1.mp3</value>
		</property>
		<property name="frequencyInKHz">
			<value>44.0999985</value>
		</property>
		<property name="channelCount">
			<value>2</value>
		</property>
		<property name="length">
			<value>2.063673469387755</value>
		</property>
		<relationship name="masterAssetFolder">
			<destination>{d72e42ed-61d3-471d-9c5a-b5cebd374c05}</destination>
		</relationship>
	</object>
</objects>
